factsumm/__init__.py
factsumm/version.py
factsumm/utils/__init__.py
factsumm/utils/level_entity.py
factsumm/utils/level_sentence.py
factsumm/utils/utils.py
factsumm-0.1.2.dist-info/LICENSE
factsumm-0.1.2.dist-info/METADATA
factsumm-0.1.2.dist-info/WHEEL
factsumm-0.1.2.dist-info/top_level.txt
factsumm-0.1.2.dist-info/RECORD
