Metadata-Version: 2.1
Name: factsumm
Version: 0.1.2
Summary: FactSumm: Factual Consistency Scorer for Abstractive Summarization
Home-page: https://github.com/huffon/factsumm
Author: Hoon Heo
License: Apache 2.0
Platform: UNKNOWN
Classifier: Intended Audience :: Developers
Classifier: Intended Audience :: Science/Research
Classifier: Programming Language :: Python :: 3
Classifier: Topic :: Scientific/Engineering :: Artificial Intelligence
Requires-Python: >=3.6.0
Requires-Dist: transformers (>=4.6.0)
Requires-Dist: pysbd
Requires-Dist: bert-score
Requires-Dist: rich
Requires-Dist: sumeval
Requires-Dist: stanford-openie
Requires-Dist: flair
Requires-Dist: dataclasses ; python_version < "3.7"
